pythena/Athena.py
pythena/Exceptions.py
pythena/Utils.py
pythena/__init__.py
pythena-1.6.0.dist-info/LICENSE
pythena-1.6.0.dist-info/METADATA
pythena-1.6.0.dist-info/WHEEL
pythena-1.6.0.dist-info/top_level.txt
pythena-1.6.0.dist-info/RECORD
