Metadata-Version: 2.1
Name: pythena
Version: 1.6.0
Summary: A simple athena wrapper leveraging boto3 to execute queries and return results while only requiring a database and a query string.
Home-page: https://github.com/chrispruitt/pythena
Author: chris.pruitt
Author-email: chris.pruitt15@gmail.com
License: Mozilla Public License Version 2.0
Platform: UNKNOWN
Requires-Dist: pandas (>=0.22.0)
Requires-Dist: boto3 (>=1.9.90)
Requires-Dist: botocore (>=1.12.90)
Requires-Dist: retrying (>=1.3.3)
